tests/__init__.py
tests/url_test.py
url_adjust/__init__.py
url_adjust/url.py
urlAdjust-0.1.2.dist-info/LICENSE
urlAdjust-0.1.2.dist-info/METADATA
urlAdjust-0.1.2.dist-info/WHEEL
urlAdjust-0.1.2.dist-info/top_level.txt
urlAdjust-0.1.2.dist-info/RECORD
