Metadata-Version: 2.1
Name: urlAdjust
Version: 0.1.2
Summary: UrlAdjust is a Python package that help developer generate get http request url with template and adjustment info. It aims to simplify the url generation process for get http request url. 
Home-page: https://github.com/F-0-X/UrlAdjust
Author: Yu Xing
Author-email: f0x.sideproject@gmail.com
Classifier: Programming Language :: Python :: 3
Classifier: License :: OSI Approved :: MIT License
Classifier: Operating System :: OS Independent
Requires-Python: >=3.9
License-File: LICENSE
